equalityml/__init__.py
equalityml/fair.py
equalityml/stats.py
equalityml/threshold.py
tests/__init__.py
tests/test_fair.py
tests/test_stats.py
tests/test_threshold.py
equalityml_fork2-0.1.2.dist-info/LICENSE
equalityml_fork2-0.1.2.dist-info/METADATA
equalityml_fork2-0.1.2.dist-info/WHEEL
equalityml_fork2-0.1.2.dist-info/top_level.txt
equalityml_fork2-0.1.2.dist-info/RECORD
