Metadata-Version: 2.1
Name: equalityml-fork2
Version: 0.1.2
Summary: Algorithms for evaluating fairness metrics and mitigating unfairness in supervised machine learning
Home-page: https://equalityai.com
Author: Ben Brintz, Mark Zhang, James Ng, Janice Davis, Jared Hansen, Ji won Chang, João Granja, Rizwan Muhammad
Author-email: support@equalityai.com
Project-URL: Website, https://equalityai.com
Project-URL: Manifesto, https://equalityai.com/community/#manifesto
Project-URL: GitHub, https://github.com/EqualityAI/EqualityML
Project-URL: Slack, https://equalityai.slack.com/ssb/redirect#/shared-invite/email
Classifier: Programming Language :: Python :: 3.7
Classifier: Programming Language :: Python :: 3.8
Classifier: Programming Language :: Python :: 3.9
Classifier: Programming Language :: Python :: 3.10
Classifier: License :: OSI Approved :: Apache Software License
Classifier: Operating System :: OS Independent
Requires-Python: >=3.7
License-File: LICENSE
Requires-Dist: BlackBoxAuditing
Requires-Dist: aif360-fork2 (>=0.5.0)
Requires-Dist: dalex (>=1.5.0)
Requires-Dist: fairlearn (>=0.7.0)
Requires-Dist: pandas (>=1.2.5)
Requires-Dist: numpy (>=1.20.3)
Requires-Dist: scikit-learn (>=0.22.1)
Provides-Extra: doc
Requires-Dist: sphinx ; extra == 'doc'
Provides-Extra: tests
Requires-Dist: pytest (>=3.5.0) ; extra == 'tests'
Requires-Dist: pytest-cov (>=2.8.1) ; extra == 'tests'
